{
  "teams": [
    {
      "id": 1,
      "author": {
        "img": "https://github.com/mdo.png",
        "first_name": "Kim",
        "last_name": "To"
      },
      "views" : 6,
      "leads": 62,
      "created_at": "2023-06-02T14:41:36-08:00"
    },
    {
      "id": 2,
      "author": {
        "img": "https://github.com/mdo.png",
        "first_name": "Maëlle",
        "last_name": "Krayon"
      },
      "views" : 9,
      "leads": 64,
      "created_at": "2022-06-02T14:41:36-08:00"
    },
    {
      "id": 3,
      "author": {
        "img": "https://github.com/mdo.png",
        "first_name": "Léo",
        "last_name": "Sambuc"
      },
      "views" : 7,
      "leads": 56,
      "created_at": "2023-06-20T14:41:36-08:00"
    },
    {
      "id": 4,
      "author": {
        "img": "https://github.com/mdo.png",
        "first_name": "Paul",
        "last_name": "Wilstein"
      },
      "views" : 10,
      "leads": 67,
      "created_at": "2023-06-19T14:41:36-08:00"
    },
    {
      "id": 5,
      "author": {
        "img": "https://github.com/mdo.png",
        "first_name": "Tom",
        "last_name": "Bourguignon"
      },
      "views" : 5,
      "leads": 26,
      "created_at": "2021-06-02T14:41:36-08:00"
    },
    {
      "id": 6,
      "author": {
        "img": "https://github.com/mdo.png",
        "first_name": "Luc",
        "last_name": "Tyfen"
      },
      "views" : 8,
      "leads": 55,
      "created_at": "2023-05-20T14:41:36-08:00"
    }
  ]
}
